[{"Usuario":"Erick","Comentario":"Estuvo Aceptable","Calificacion":"Falso","id":"2"},{"Usuario":"Erick","Comentario":"Estuvo Aceptable","Calificacion":"Falso","id":"2"},{"Usuario":"Erick","Comentario":"","Calificacion":"Falso","id":""},{"Usuario":"Erick","Comentario":"Estuvo Aceptable","Calificacion":"Falso","id":"123"},{"Usuario":"Erick","Comentario":"Estuvo Aceptable","Calificacion":"10","id":"1234eq"},{"Usuario":"Pablo","Comentario":"XD MALISIMA","Calificacion":"","id":"1"},{"Usuario":"Pablo","Comentario":"XD MALISIMA","Calificacion":"","id":"1"},{"Usuario":"Pablo","Comentario":"Malisima","Calificacion":"1","id":"34"},{"Usuario":"KAKA","Comentario":"XD MALISIMA","Calificacion":"1","id":"1"},{"Usuario":"KAKA","Comentario":"","Calificacion":"","id":""},{"Usuario":"KAKA","Comentario":"","Calificacion":"","id":""},{"Usuario":"KAKA","Comentario":"","Calificacion":"","id":""},{"Usuario":"Erick","Comentario":"Estuvo Aceptable","Calificacion":"10","id":"112","actividad":[{"Fecha":"20/20/2019","id":1,"Hora":"8:00 pm","Lugar":"Parque de ACTIVIDADES","Tipo":"Diversion","Cantidad":"10","Expositor":"Alejandro Sanza","Descripcion":" Sera de gran alegria"},{"id":"1","Fecha":"2019-12-16","Hora":"02:03","Lugar":"d","Tipo":"Para gente cool","Expositor":"Pedro Escamozo","Cantidad":"230","Descripcion":"sera de gran diversion"},{"id":"34","Fecha":"2019-12-04","Hora":"23:23","Lugar":"Salon 6","Tipo":"Diversion ","Expositor":"Pedro Escamozo","Cantidad":"100","Descripcion":"Sera de garan deiverson"}]},{"Usuario":"Erick","Comentario":"Estuvo Aceptable","Calificacion":"9","id":"1","Actividad":"34"},{"Usuario":"Erick","Comentario":"XD MALISIMA","Calificacion":"6","id":"555","Actividad":"34"},{"Usuario":"Erick","Comentario":"XD MALISIMA","Calificacion":"6","id":"555","Actividad":"34"},{"Usuario":"Erick","Comentario":"se va","Calificacion":"5","id":"25","Actividad":"34","Tipo":""},{"Usuario":"Erick","Comentario":"se va","Calificacion":"6","id":"444","Actividad":"34","Tipo":"Diversion "},{"Usuario":"Pablo","Comentario":"lol","Calificacion":"9","id":"1000","Tipo":""},{"Usuario":"Pablo","Comentario":"xd","Calificacion":"9","id":"23","Actividad":"34","Tipo":"Diversion "},{"Usuario":"KAKA","Comentario":"LOL","Calificacion":"10","id":"200","Actividad":"34","Tipo":"Diversion "},{"Usuario":"Erick","Comentario":"estuvo en todoooo","Calificacion":"9","id":"250000","Actividad":"6666","Tipo":"Conferencia"},{"Usuario":"Pablo","Comentario":"Estuvo Aceptable","Calificacion":"10","id":"","Actividad":"777","Tipo":"prueba"},{"Usuario":"Erick","Comentario":"Estuvo Aceptable","Calificacion":"10","id":"444444","Actividad":"777","Tipo":"prueba"},{"Usuario":"","Comentario":"XD MALISIMA","Calificacion":"5","id":"4444","Actividad":"1","Tipo":"Para gente cool"}]